centraal_dataframework/__init__.py
centraal_dataframework/blueprints.py
centraal_dataframework/email_sender.py
centraal_dataframework/excepciones.py
centraal_dataframework/resources.py
centraal_dataframework/runner.py
centraal_dataframework/tasks.py
centraal_dataframework/utils.py
centraal_dataframework-0.1.3.dist-info/LICENSE
centraal_dataframework-0.1.3.dist-info/METADATA
centraal_dataframework-0.1.3.dist-info/WHEEL
centraal_dataframework-0.1.3.dist-info/RECORD
