Metadata-Version: 2.1
Name: centraal_dataframework
Version: 0.1.3
Summary: Utilidades para interactuar con Azure Datalake.
Home-page: https://github.com/centraal-api/centraal-dataframework
License: Apache-2.0
Author: centraal.studio
Author-email: equipo@centraal.studio
Requires-Python: >=3.8,<3.10
Classifier: Development Status :: 2 - Pre-Alpha
Classifier: Intended Audience :: Developers
Classifier: License :: OSI Approved :: Apache Software License
Classifier: Natural Language :: English
Classifier: Programming Language :: Python :: 3
Classifier: Programming Language :: Python :: 3.8
Classifier: Programming Language :: Python :: 3.9
Classifier: Programming Language :: Python :: 3.10
Provides-Extra: dev
Provides-Extra: doc
Provides-Extra: test
Requires-Dist: azure-datalake-utils (>=0.5.8,<1.0)
Requires-Dist: azure-functions (>1.0,<2.0)
Requires-Dist: black (>=22.3.0,<23.0.0) ; extra == "test"
Requires-Dist: bump2version (>=1.0.1,<2.0.0) ; extra == "dev"
Requires-Dist: flake8 (>=3.9.2) ; extra == "test"
Requires-Dist: flake8-docstrings (>=1.6.0,<2.0.0) ; extra == "test"
Requires-Dist: great-expectations (>=0.17,<1.0)
Requires-Dist: isort (>=5.8.0,<6.0.0) ; extra == "test"
Requires-Dist: jupyter (>=1.0) ; extra == "dev"
Requires-Dist: markupsafe (==2.0.1) ; extra == "test"
Requires-Dist: mkdocs (>=1.3,<2.0) ; extra == "doc"
Requires-Dist: mkdocs-autorefs (>=0.3,<0.4) ; extra == "doc"
Requires-Dist: mkdocs-include-markdown-plugin (>=1.0.0,<2.0.0) ; extra == "doc"
Requires-Dist: mkdocs-material (>=8.0,<9.0) ; extra == "doc"
Requires-Dist: mkdocs-material-extensions (>=1.0.1,<2.0.0)
Requires-Dist: mkdocstrings[python] (>=0.19.0,<0.20.0) ; extra == "doc"
Requires-Dist: pip (>=22.0) ; extra == "dev"
Requires-Dist: pre-commit (>=2.12.0,<3.0.0) ; extra == "dev"
Requires-Dist: pytest (>=6.2.4) ; extra == "test"
Requires-Dist: pytest-cov (>=2.12.0) ; extra == "test"
Requires-Dist: python-dotenv (>=1.0.0,<2.0) ; extra == "dev"
Requires-Dist: toml (>=0.10.2,<0.11.0) ; extra == "dev"
Requires-Dist: tox (>=3.20.1,<4.0.0) ; extra == "dev"
Requires-Dist: twine (>=3.3.0,<4.0.0) ; extra == "dev"
Requires-Dist: virtualenv (>=20.2.2,<21.0.0) ; extra == "dev"
